<?xml version="1.0" encoding="UTF-8" standalone="yes"?>
<?mso-application progid="Excel.Sheet"?>
<Workbook xmlns="urn:schemas-microsoft-com:office:spreadsheet" xmlns:o="urn:schemas-microsoft-com:office:office" xmlns:x="urn:schemas-microsoft-com:office:excel" xmlns:ss="urn:schemas-microsoft-com:office:spreadsheet" xmlns:html="http://www.w3.org/TR/REC-html40" xmlns:dt="uuid:C2F41010-65B3-11d1-A29F-00AA00C14882"><DocumentProperties xmlns="urn:schemas-microsoft-com:office:office"><LastAuthor>武库元凯</LastAuthor><Created>2021-03-24T10:02:00Z</Created><LastSaved>2021-05-12T06:02:12Z</LastSaved></DocumentProperties><CustomDocumentProperties xmlns="urn:schemas-microsoft-com:office:office"><KSOProductBuildVer dt:dt="string">2052-11.1.0.10463</KSOProductBuildVer><ICV dt:dt="string">426130A8E63D48219839CDEC84E56F5F</ICV></CustomDocumentProperties><ExcelWorkbook xmlns="urn:schemas-microsoft-com:office:excel"><WindowWidth>28800</WindowWidth><WindowHeight>12540</WindowHeight><ProtectStructure>False</ProtectStructure><ProtectWindows>False</ProtectWindows></ExcelWorkbook><Styles><Style ss:ID="Default" ss:Name="Normal"><Alignment ss:Vertical="Center"/><Borders/><Font ss:FontName="宋体" x:CharSet="134" ss:Size="11" ss:Color="#000000"/><Interior/><NumberFormat/><Protection/></Style><Style ss:ID="s49"><Alignment ss:Vertical="Center"/><Borders/><Font ss:FontName="宋体" x:CharSet="134" ss:Size="11" ss:Color="#000000"/><Interior/><NumberFormat/><Protection/></Style><Style ss:ID="s50"><Alignment ss:Horizontal="Center" ss:Vertical="Center"/></Style><Style ss:ID="s51"><Alignment ss:Horizontal="Center" ss:Vertical="Bottom"/><Borders><Border ss:Position="Bottom" ss:LineStyle="Continuous" ss:Weight="1"/><Border ss:Position="Left" ss:LineStyle="Continuous" ss:Weight="1"/><Border ss:Position="Right" ss:LineStyle="Continuous" ss:Weight="1"/><Border ss:Position="Top" ss:LineStyle="Continuous" ss:Weight="1"/></Borders><Font ss:FontName="微软雅黑" x:CharSet="134" x:Family="Swiss" ss:Size="11" ss:Color="#000000"/><Interior ss:Color="#C0C0C0" ss:Pattern="Solid"/></Style><Style ss:ID="s52"><Alignment ss:Horizontal="Center" ss:Vertical="Bottom"/><Font ss:FontName="微软雅黑" x:CharSet="134" x:Family="Swiss" ss:Size="11" ss:Color="#000000"/><Interior/></Style><Style ss:ID="s53"><Alignment ss:Horizontal="Center" ss:Vertical="Center"/><Interior/></Style></Styles><Worksheet ss:Name="EquipSC"><Table ss:ExpandedColumnCount="4" ss:ExpandedRowCount="9" x:FullColumns="1" x:FullRows="1" ss:DefaultColumnWidth="54" ss:DefaultRowHeight="13.5"><Column ss:Index="1" ss:StyleID="s50" ss:AutoFitWidth="0"/><Column ss:Index="2" ss:StyleID="s50" ss:AutoFitWidth="0" ss:Width="101.25"/><Column ss:StyleID="s50" ss:AutoFitWidth="0" ss:Width="92.25"/><Column ss:StyleID="s50" ss:AutoFitWidth="0" ss:Width="77.25"/><Row><Cell ss:StyleID="s50"><Data ss:Type="String">编号</Data></Cell><Cell ss:StyleID="s50"><Data ss:Type="String">目标物品</Data></Cell><Cell ss:StyleID="s50"><Data ss:Type="String">所需材料</Data></Cell><Cell ss:StyleID="s50"><Data ss:Type="String">所需合成数量</Data></Cell></Row><Row><Cell ss:StyleID="s51"><Data ss:Type="String">uint|mID</Data></Cell><Cell ss:StyleID="s51"><Data ss:Type="String">int|targetPropID</Data></Cell><Cell ss:StyleID="s51"><Data ss:Type="String">int|uesdPropID</Data></Cell><Cell ss:StyleID="s51"><Data ss:Type="String">int|uesdNum</Data></Cell></Row><Row><Cell ss:StyleID="s51"><Data ss:Type="String">both</Data></Cell><Cell ss:StyleID="s51"><Data ss:Type="String">both</Data></Cell><Cell ss:StyleID="s51"><Data ss:Type="String">both</Data></Cell><Cell ss:StyleID="s51"><Data ss:Type="String">both</Data></Cell></Row><Row><Cell ss:StyleID="s52"><Data ss:Type="Number">1</Data></Cell><Cell ss:StyleID="s53"><Data ss:Type="Number">2000250</Data></Cell><Cell ss:StyleID="s52"><Data ss:Type="Number">0</Data></Cell><Cell ss:StyleID="s52"><Data ss:Type="Number">0</Data></Cell></Row><Row><Cell ss:StyleID="s52"><Data ss:Type="Number">2</Data></Cell><Cell ss:StyleID="s53"><Data ss:Type="Number">2000251</Data></Cell><Cell ss:StyleID="s53"><Data ss:Type="Number">2000250</Data></Cell><Cell ss:StyleID="s53"><Data ss:Type="Number">2</Data></Cell></Row><Row><Cell ss:StyleID="s52"><Data ss:Type="Number">3</Data></Cell><Cell ss:StyleID="s53"><Data ss:Type="Number">2000252</Data></Cell><Cell ss:StyleID="s53"><Data ss:Type="Number">2000251</Data></Cell><Cell ss:StyleID="s53"><Data ss:Type="Number">2</Data></Cell></Row><Row><Cell ss:StyleID="s52"><Data ss:Type="Number">4</Data></Cell><Cell ss:StyleID="s53"><Data ss:Type="Number">2000253</Data></Cell><Cell ss:StyleID="s53"><Data ss:Type="Number">2000252</Data></Cell><Cell ss:StyleID="s53"><Data ss:Type="Number">2</Data></Cell></Row><Row><Cell ss:StyleID="s52"><Data ss:Type="Number">5</Data></Cell><Cell ss:StyleID="s53"><Data ss:Type="Number">2000254</Data></Cell><Cell ss:StyleID="s53"><Data ss:Type="Number">2000253</Data></Cell><Cell ss:StyleID="s53"><Data ss:Type="Number">2</Data></Cell></Row><Row><Cell ss:StyleID="s52"><Data ss:Type="Number">6</Data></Cell><Cell ss:StyleID="s53"><Data ss:Type="Number">2000255</Data></Cell><Cell ss:StyleID="s53"><Data ss:Type="Number">2000254</Data></Cell><Cell ss:StyleID="s53"><Data ss:Type="Number">2</Data></Cell></Row></Table><WorksheetOptions xmlns="urn:schemas-microsoft-com:office:excel"><PageSetup><Header x:Margin="0.3"/><Footer x:Margin="0.3"/><PageMargins x:Left="0.7" x:Right="0.7" x:Top="0.75" x:Bottom="0.75"/></PageSetup><Selected/><TopRowVisible>0</TopRowVisible><LeftColumnVisible>0</LeftColumnVisible><PageBreakZoom>100</PageBreakZoom><Panes><Pane><Number>3</Number><ActiveRow>8</ActiveRow><ActiveCol>3</ActiveCol><RangeSelection>R9C4</RangeSelection></Pane></Panes><ProtectObjects>False</ProtectObjects><ProtectScenarios>False</ProtectScenarios></WorksheetOptions></Worksheet></Workbook>